snmachine/__init__.py
snmachine/analysis.py
snmachine/chisq.py
snmachine/gps.py
snmachine/parametric_models.py
snmachine/snaugment.py
snmachine/snclassifier.py
snmachine/sndata.py
snmachine/snfeatures.py
snmachine/tsne_plot.py
snmachine/example_data/SPCC_SUBSET.tar.gz
snmachine/example_data/eigenvals.npz
snmachine/example_data/example_data_for_tests.pckl
snmachine/example_data/example_test_dataset.pckl
snmachine/example_data/plasticc_train_lightcurves.csv
snmachine/example_data/plasticc_train_metadata.csv
snmachine/example_data/sniabcii_test_lightcurves_example.csv
snmachine/example_data/sniabcii_test_metadata_example.csv
snmachine/example_data/output_spcc_no_z/features/spcc_all_karpenka.dat
snmachine/example_data/output_spcc_no_z/features/spcc_all_newling.dat
snmachine/example_data/output_spcc_no_z/features/spcc_all_templates.dat
snmachine/example_data/output_spcc_no_z/features/spcc_all_wavelets.dat
snmachine/example_data/output_spcc_no_z/features/spcc_all_wavelets_PCA_mean.dat
snmachine/example_data/output_spcc_no_z/features/spcc_all_wavelets_PCA_vals.dat
snmachine/example_data/output_spcc_no_z/features/spcc_all_wavelets_PCA_vec.dat
snmachine/utils/__init__.py
snmachine/utils/config.yml
snmachine/utils/imblearn_augment.py
snmachine/utils/plasticc_feature_engineering.py
snmachine/utils/plasticc_make_predictions.py
snmachine/utils/plasticc_pipeline.py
snmachine/utils/plasticc_utils.py
snmachine-2.0.0.post3.dist-info/LICENSE
snmachine-2.0.0.post3.dist-info/METADATA
snmachine-2.0.0.post3.dist-info/WHEEL
snmachine-2.0.0.post3.dist-info/top_level.txt
snmachine-2.0.0.post3.dist-info/RECORD
