Metadata-Version: 2.1
Name: snmachine
Version: 2.0.0.post3
Summary: Machine learning code for photometric supernova classification
Home-page: https://github.com/LSSTDESC/snmachine
Author: Michelle Lochner
Author-email: dr.michelle.lochner@gmail.com
License: BSD-3-Clause License
Platform: UNKNOWN
License-File: LICENSE
Requires-Dist: astropy (>=1.1.2)
Requires-Dist: matplotlib (>=3.0.0)
Requires-Dist: numpy (>=1.18.4)
Requires-Dist: scikit-learn
Requires-Dist: scipy (>=1.4.0)
Requires-Dist: george (>=0.3.0)
Requires-Dist: iminuit
Requires-Dist: pandas (>=0.23.0)
Requires-Dist: pywavelets (>=0.4.0)
Requires-Dist: sncosmo (==2.1.0)
Requires-Dist: nose (>=1.3.7)
Requires-Dist: future (>=0.16)
Requires-Dist: pyyaml (>=3.13)
Requires-Dist: seaborn
Requires-Dist: lightgbm
Requires-Dist: setuptools-scm
